container_tagbot/__init__.py
container_tagbot-3.2.1.dist-info/licenses/LICENSE
container_tagbot-3.2.1.dist-info/METADATA
container_tagbot-3.2.1.dist-info/WHEEL
container_tagbot-3.2.1.dist-info/entry_points.txt
container_tagbot-3.2.1.dist-info/top_level.txt
container_tagbot-3.2.1.dist-info/RECORD
