Metadata-Version: 2.4
Name: container-tagbot
Version: 3.2.1
Summary: Retags a Container in a Container Registry without the need for Docker
License-Expression: MIT
Requires-Python: >=3.13
License-File: LICENSE
Requires-Dist: click>=8.2.1
Requires-Dist: loguru>=0.7.3
Requires-Dist: requests>=2.32.4
Dynamic: license-file
